odoo/addons/base_revision/README.rst
odoo/addons/base_revision/__init__.py
odoo/addons/base_revision/__manifest__.py
odoo/addons/base_revision/i18n/base_revision.pot
odoo/addons/base_revision/i18n/es.po
odoo/addons/base_revision/i18n/it.po
odoo/addons/base_revision/i18n/pt.po
odoo/addons/base_revision/i18n/tr.po
odoo/addons/base_revision/models/__init__.py
odoo/addons/base_revision/models/base_revision.py
odoo/addons/base_revision/readme/CONTRIBUTORS.md
odoo/addons/base_revision/readme/DESCRIPTION.md
odoo/addons/base_revision/static/description/icon.png
odoo/addons/base_revision/static/description/index.html
odoo/addons/base_revision/tests/__init__.py
odoo/addons/base_revision/tests/base_revision_tester.py
odoo/addons/base_revision/tests/test_base_revision.py
odoo_addon_base_revision-18.0.1.0.0.8.dist-info/METADATA
odoo_addon_base_revision-18.0.1.0.0.8.dist-info/WHEEL
odoo_addon_base_revision-18.0.1.0.0.8.dist-info/top_level.txt
odoo_addon_base_revision-18.0.1.0.0.8.dist-info/RECORD
